src/icon.ico
src/main.py
src/api/__init__.py
src/api/article.py
src/api/base.py
src/api/bolo.py
src/api/chat.py
src/api/chatroom.py
src/api/enum.py
src/api/redpacket.py
src/api/user.py
src/config/__init__.py
src/config/auth.py
src/config/bolo.py
src/config/chat.py
src/config/redpacket.py
src/core/__init__.py
src/core/blacklist.py
src/core/chat.py
src/core/chatroom.py
src/core/command.py
src/core/decorators.py
src/core/fishpi.py
src/core/notification.py
src/core/redpacket.py
src/core/user.py
src/core/ws.py
src/core/initor/__init__.py
src/core/initor/bolo_initor.py
src/core/initor/chatroom_initor.py
src/core/initor/cli_initor.py
src/core/initor/defualt_initor.py
src/core/initor/env_initor.py
src/core/initor/file_initor.py
src/core/initor/init_chan.py
src/core/initor/login_initor.py
src/utils/__init__.py
src/utils/file.py
src/utils/version.py
fishpi_pyclient-2.2.1.dist-info/LICENSE
fishpi_pyclient-2.2.1.dist-info/METADATA
fishpi_pyclient-2.2.1.dist-info/WHEEL
fishpi_pyclient-2.2.1.dist-info/entry_points.txt
fishpi_pyclient-2.2.1.dist-info/top_level.txt
fishpi_pyclient-2.2.1.dist-info/RECORD
