Metadata-Version: 2.1
Name: fishpi-pyclient
Version: 2.2.1
Summary: 摸鱼派聊天室python客户端
Home-page: https://github.com/gakkiyomi/fishpi-pyclient
Author: gakkiyomi
Author-email: gakkiyomi@gmail.com
License: MIT
Classifier: License :: OSI Approved :: MIT License
Classifier: Programming Language :: Python
Classifier: Programming Language :: Python :: 3.12
Classifier: Programming Language :: Python :: Implementation :: CPython
Classifier: Programming Language :: Python :: Implementation :: PyPy
Requires-Python: >=3.12
License-File: LICENSE
Requires-Dist: requests
Requires-Dist: websocket-client
Requires-Dist: click
Requires-Dist: schedule
Requires-Dist: objprint
Requires-Dist: colorama
Requires-Dist: termcolor
Requires-Dist: prettytable
Requires-Dist: bs4
Requires-Dist: html2text
Requires-Dist: plyer
Provides-Extra: macos
Requires-Dist: pyobjus; extra == "macos"
